multimorbidity_hypergraphs/__init__.py
multimorbidity_hypergraphs/hypergraph_tools.py
multimorbidity_hypergraphs-0.3.5.dist-info/LICENSE
multimorbidity_hypergraphs-0.3.5.dist-info/METADATA
multimorbidity_hypergraphs-0.3.5.dist-info/WHEEL
multimorbidity_hypergraphs-0.3.5.dist-info/top_level.txt
multimorbidity_hypergraphs-0.3.5.dist-info/RECORD
