Metadata-Version: 2.1
Name: multimorbidity-hypergraphs
Version: 0.3.5
Summary: A toolbox for large scale data analysis using hypergraphs
Home-page: https://github.com/jim-rafferty/multimorbidity_hypergraphs
Author: Jim Rafferty
Author-email: j.m.rafferty@swansea.ac.uk
License: UNKNOWN
Project-URL: Bug Tracker, https://github.com/jim-rafferty/multimorbidity_hypergraphs/issues
Platform: UNKNOWN
Classifier: Programming Language :: Python :: 3
Classifier: License :: OSI Approved :: GNU General Public License v3 (GPLv3)
Classifier: Operating System :: OS Independent
Requires-Python: >=3.5
License-File: LICENSE
Requires-Dist: numpy
Requires-Dist: scipy
Requires-Dist: numba
